MANIFEST.in
README.rst
setup.py
docs/HISTORY.txt
docs/LICENSE.GPL
docs/LICENSE.txt
ftw/__init__.py
ftw.deploy.egg-info/PKG-INFO
ftw.deploy.egg-info/SOURCES.txt
ftw.deploy.egg-info/dependency_links.txt
ftw.deploy.egg-info/entry_points.txt
ftw.deploy.egg-info/namespace_packages.txt
ftw.deploy.egg-info/not-zip-safe
ftw.deploy.egg-info/top_level.txt
ftw/deploy/__init__.py
ftw/deploy/gitsupport.py
ftw/deploy/sshsupport.py
ftw/deploy/utils.py
ftw/deploy/command/__init__.py
ftw/deploy/command/formatter.py
ftw/deploy/command/help.py
ftw/deploy/command/init.py
ftw/deploy/command/rerun.py
ftw/deploy/command/setup.py
ftw/deploy/command/ssh.py
ftw/deploy/command/update.py
ftw/deploy/scripts/post-receive
ftw/deploy/templates/__init__.py
ftw/deploy/templates/base.py
ftw/deploy/templates/plone.py
ftw/deploy/templates/plone/deploy/after_push
ftw/deploy/templates/plone/deploy/pull
ftw/deploy/templates/plone/deploy/update_plone
ftw/deploy/templates/plone/scripts/setup-git-remotes
ftw/deploy/tests/__init__.py
ftw/deploy/tests/conftest.py
ftw/deploy/tests/test_command_help.py
ftw/deploy/tests/test_command_init.py
ftw/deploy/tests/test_command_init_plone.py
ftw/deploy/tests/test_command_rerun.py
ftw/deploy/tests/test_command_setup.py
ftw/deploy/tests/test_command_ssh.py
ftw/deploy/tests/test_command_update.py
ftw/deploy/tests/test_command_version.py
ftw/deploy/tests/bin_stubs/recording-bin-stub
ftw/deploy/tests/bin_stubs/scp
ftw/deploy/tests/bin_stubs/ssh