Metadata-Version: 1.1
Name: ftw.deploy
Version: 1.1.0
Summary: Tooling and scripts for git push based deployment at 4teamwork.
Home-page: https://github.com/4teamwork/ftw.deploy
Author: 4teamwork AG
Author-email: mailto:info@4teamwork.ch
License: GPL2
Keywords: ftw deploy
Platform: UNKNOWN
Classifier: Intended Audience :: Developers
